hy/__init__.py
hy/main.py
hy_tutorial-0.0.1.dist-info/LICENSE
hy_tutorial-0.0.1.dist-info/METADATA
hy_tutorial-0.0.1.dist-info/WHEEL
hy_tutorial-0.0.1.dist-info/top_level.txt
hy_tutorial-0.0.1.dist-info/RECORD
