Metadata-Version: 2.1
Name: hy-tutorial
Version: 0.0.1
Summary: A small example package
Author-email: Zaid Waqi <zaidwaqi@gmail.com>
Project-URL: Homepage, https://github.com/zaidwaqi/hy
Project-URL: Issues, https://github.com/pypa/zaidwaqi/hy/issues
Classifier: Programming Language :: Python :: 3
Classifier: License :: OSI Approved :: MIT License
Classifier: Operating System :: OS Independent
Requires-Python: >=3.11
License-File: LICENSE
